{
  "site": "site0",
  "tile": {
    "before": "data/KEMET1_BeforeAfter/KEMET1_BeforeAfter_Tiles/site0_before_2024.tif",
    "after": "data/KEMET1_BeforeAfter/KEMET1_BeforeAfter_Tiles/site0_after_2025.tif",
    "shape": [
      6,
      262,
      262
    ],
    "tile_ha": 686.4,
    "crs": "EPSG:32636",
    "bounds": {
      "left": 267140.0,
      "bottom": 3395610.0,
      "right": 269760.0,
      "top": 3398230.0
    }
  },
  "rf": {
    "prob": 0.5822,
    "n_features": 44,
    "threshold": 0.29
  },
  "spectral": {
    "mean_delta_ndvi": -0.0286,
    "mean_delta_ndbi": 0.0256,
    "spectral_signal": 0.0649
  },
  "fusion": {
    "score": 0.4011,
    "weights": {
      "rf": 0.65,
      "spectral": 0.35
    }
  },
  "alarm": "Red Alert",
  "encroachment": {
    "total_ha": 26.08,
    "n_clusters": 28,
    "clusters": [
      {
        "id": 87,
        "ha": 2.71,
        "bbox_px": [
          156,
          180,
          181,
          198
        ]
      },
      {
        "id": 28,
        "ha": 2.45,
        "bbox_px": [
          127,
          67,
          161,
          80
        ]
      },
      {
        "id": 132,
        "ha": 1.42,
        "bbox_px": [
          195,
          223,
          213,
          238
        ]
      },
      {
        "id": 46,
        "ha": 1.39,
        "bbox_px": [
          104,
          93,
          119,
          105
        ]
      },
      {
        "id": 8,
        "ha": 1.26,
        "bbox_px": [
          205,
          37,
          222,
          48
        ]
      },
      {
        "id": 1,
        "ha": 1.18,
        "bbox_px": [
          229,
          4,
          246,
          12
        ]
      },
      {
        "id": 103,
        "ha": 1.14,
        "bbox_px": [
          118,
          208,
          135,
          220
        ]
      },
      {
        "id": 6,
        "ha": 1.03,
        "bbox_px": [
          97,
          30,
          114,
          39
        ]
      },
      {
        "id": 38,
        "ha": 0.98,
        "bbox_px": [
          180,
          87,
          196,
          95
        ]
      },
      {
        "id": 54,
        "ha": 0.95,
        "bbox_px": [
          229,
          114,
          247,
          120
        ]
      },
      {
        "id": 10,
        "ha": 0.87,
        "bbox_px": [
          42,
          42,
          56,
          52
        ]
      },
      {
        "id": 42,
        "ha": 0.79,
        "bbox_px": [
          216,
          90,
          231,
          97
        ]
      },
      {
        "id": 3,
        "ha": 0.76,
        "bbox_px": [
          100,
          12,
          117,
          18
        ]
      },
      {
        "id": 76,
        "ha": 0.76,
        "bbox_px": [
          243,
          151,
          259,
          157
        ]
      },
      {
        "id": 84,
        "ha": 0.7,
        "bbox_px": [
          240,
          172,
          255,
          178
        ]
      },
      {
        "id": 112,
        "ha": 0.68,
        "bbox_px": [
          92,
          215,
          105,
          228
        ]
      },
      {
        "id": 36,
        "ha": 0.67,
        "bbox_px": [
          124,
          85,
          141,
          90
        ]
      },
      {
        "id": 111,
        "ha": 0.67,
        "bbox_px": [
          227,
          214,
          241,
          223
        ]
      },
      {
        "id": 82,
        "ha": 0.66,
        "bbox_px": [
          58,
          162,
          73,
          167
        ]
      },
      {
        "id": 53,
        "ha": 0.6,
        "bbox_px": [
          248,
          112,
          261,
          118
        ]
      },
      {
        "id": 125,
        "ha": 0.59,
        "bbox_px": [
          28,
          221,
          37,
          236
        ]
      },
      {
        "id": 52,
        "ha": 0.58,
        "bbox_px": [
          176,
          112,
          192,
          117
        ]
      },
      {
        "id": 61,
        "ha": 0.58,
        "bbox_px": [
          192,
          123,
          208,
          129
        ]
      },
      {
        "id": 107,
        "ha": 0.57,
        "bbox_px": [
          242,
          210,
          249,
          219
        ]
      },
      {
        "id": 63,
        "ha": 0.54,
        "bbox_px": [
          48,
          128,
          61,
          134
        ]
      },
      {
        "id": 2,
        "ha": 0.52,
        "bbox_px": [
          248,
          5,
          261,
          10
        ]
      },
      {
        "id": 47,
        "ha": 0.52,
        "bbox_px": [
          4,
          101,
          13,
          107
        ]
      },
      {
        "id": 96,
        "ha": 0.51,
        "bbox_px": [
          243,
          194,
          253,
          200
        ]
      }
    ]
  },
  "generated_at": "2026-07-03"
}